[
    {
        "date": "Sep 7",
        "player": {
            "id": "12682",
            "slug": "claudio-pizarro",
            "name": "Claudio Pizarro"
        },
        "fromClub": {
            "name": "No team",
            "id": null,
            "slug": null
        },
        "toClub": {
            "name": "Werder Bremen",
            "id": "137",
            "slug": "werder-bremen"
        },
        "status": "Free"
    },
    {
        "date": "Sep 1",
        "player": {
            "id": "100925",
            "slug": "lukasz-zaluska",
            "name": "Lukasz Zaluska"
        },
        "fromClub": {
            "name": "No team",
            "id": null,
            "slug": null
        },
        "toClub": {
            "name": "SV Darmstadt 98",
            "id": "3812",
            "slug": "sv-darmstadt-98"
        },
        "status": "Free"
    },
    {
        "date": "Aug 31",
        "player": {
            "id": null,
            "slug": null,
            "name": "Ismail Azzaoui"
        },
        "fromClub": {
            "name": "Tottenham Hotspur",
            "id": "367",
            "slug": "tottenham-hotspur"
        },
        "toClub": {
            "name": "VfL Wolfsburg",
            "id": "138",
            "slug": "vfl-wolfsburg"
        },
        "status": "Undisclosed"
    },
    {
        "date": "Aug 31",
        "player": {
            "id": "155246",
            "slug": "julian-draxler",
            "name": "Julian Draxler"
        },
        "fromClub": {
            "name": "Schalke 04",
            "id": "133",
            "slug": "schalke-04"
        },
        "toClub": {
            "name": "VfL Wolfsburg",
            "id": "138",
            "slug": "vfl-wolfsburg"
        },
        "status": "Undisclosed"
    },
    {
        "date": "Aug 31",
        "player": {
            "id": "146419",
            "slug": "javier-hernandez",
            "name": "Javier Hernández"
        },
        "fromClub": {
            "name": "Manchester United",
            "id": "360",
            "slug": "manchester-united"
        },
        "toClub": {
            "name": "Bayer Leverkusen",
            "id": "131",
            "slug": "bayer-leverkusen"
        },
        "status": "Undisclosed"
    },
    {
        "date": "Aug 31",
        "player": {
            "id": "43337",
            "slug": "aaron-hunt",
            "name": "Aaron Hunt"
        },
        "fromClub": {
            "name": "VfL Wolfsburg",
            "id": "138",
            "slug": "vfl-wolfsburg"
        },
        "toClub": {
            "name": "Hamburg SV",
            "id": "127",
            "slug": "hamburg-sv"
        },
        "status": "Undisclosed"
    },
    {
        "date": "Aug 31",
        "player": {
            "id": null,
            "slug": null,
            "name": "Koo Ja-cheol"
        },
        "fromClub": {
            "name": "Mainz",
            "id": "2950",
            "slug": "mainz"
        },
        "toClub": {
            "name": "FC Augsburg",
            "id": "3841",
            "slug": "fc-augsburg"
        },
        "status": "Undisclosed"
    },
    {
        "date": "Aug 31",
        "player": {
            "id": "84659",
            "slug": "oliver-kirch",
            "name": "Oliver Kirch"
        },
        "fromClub": {
            "name": "Borussia Dortmund",
            "id": "124",
            "slug": "borussia-dortmund"
        },
        "toClub": {
            "name": "SC Paderborn 07",
            "id": "3307",
            "slug": "sc-paderborn-07"
        },
        "status": "Undisclosed"
    },
    {
        "date": "Aug 31",
        "player": {
            "id": "103485",
            "slug": "ivan-perisic",
            "name": "Ivan Perisic"
        },
        "fromClub": {
            "name": "VfL Wolfsburg",
            "id": "138",
            "slug": "vfl-wolfsburg"
        },
        "toClub": {
            "name": "Internazionale",
            "id": "110",
            "slug": "internazionale"
        },
        "status": "Undisclosed"
    },
    {
        "date": "Aug 31",
        "player": {
            "id": "130165",
            "slug": "dante",
            "name": "Dante"
        },
        "fromClub": {
            "name": "Bayern Munich",
            "id": "132",
            "slug": "bayern-munich"
        },
        "toClub": {
            "name": "VfL Wolfsburg",
            "id": "138",
            "slug": "vfl-wolfsburg"
        },
        "status": "Free"
    },
    {
        "date": "Aug 31",
        "player": {
            "id": "102200",
            "slug": "jakub-blaszczykowski",
            "name": "Jakub Blaszczykowski"
        },
        "fromClub": {
            "name": "Borussia Dortmund",
            "id": "124",
            "slug": "borussia-dortmund"
        },
        "toClub": {
            "name": "Fiorentina",
            "id": "109",
            "slug": "fiorentina"
        },
        "status": "Loan"
    },
    {
        "date": "Aug 31",
        "player": {
            "id": "186432",
            "slug": "adnan-januzaj",
            "name": "Adnan Januzaj"
        },
        "fromClub": {
            "name": "Manchester United",
            "id": "360",
            "slug": "manchester-united"
        },
        "toClub": {
            "name": "Borussia Dortmund",
            "id": "124",
            "slug": "borussia-dortmund"
        },
        "status": "Loan"
    },
    {
        "date": "Aug 30",
        "player": {
            "id": "134947",
            "slug": "kevin-de-bruyne",
            "name": "Kevin De Bruyne"
        },
        "fromClub": {
            "name": "VfL Wolfsburg",
            "id": "138",
            "slug": "vfl-wolfsburg"
        },
        "toClub": {
            "name": "Manchester City",
            "id": "382",
            "slug": "manchester-city"
        },
        "status": "Undisclosed"
    },
    {
        "date": "Aug 30",
        "player": {
            "id": "84701",
            "slug": "vedad-ibisevic",
            "name": "Vedad Ibisevic"
        },
        "fromClub": {
            "name": "VfB Stuttgart",
            "id": "134",
            "slug": "vfb-stuttgart"
        },
        "toClub": {
            "name": "Hertha Berlin",
            "id": "129",
            "slug": "hertha-berlin"
        },
        "status": "Undisclosed"
    },
    {
        "date": "Aug 30",
        "player": {
            "id": "184012",
            "slug": "kingsley-coman",
            "name": "Kingsley Coman"
        },
        "fromClub": {
            "name": "Juventus",
            "id": "111",
            "slug": "juventus"
        },
        "toClub": {
            "name": "Bayern Munich",
            "id": "132",
            "slug": "bayern-munich"
        },
        "status": "Loan"
    },
    {
        "date": "Aug 29",
        "player": {
            "id": "194347",
            "slug": "park-joo-ho",
            "name": "Park Joo-Ho"
        },
        "fromClub": {
            "name": "Mainz",
            "id": "2950",
            "slug": "mainz"
        },
        "toClub": {
            "name": "Borussia Dortmund",
            "id": "124",
            "slug": "borussia-dortmund"
        },
        "status": "Undisclosed"
    },
    {
        "date": "Aug 28",
        "player": {
            "id": "149945",
            "slug": "son-heung-min",
            "name": "Son Heung-Min"
        },
        "fromClub": {
            "name": "Bayer Leverkusen",
            "id": "131",
            "slug": "bayer-leverkusen"
        },
        "toClub": {
            "name": "Tottenham Hotspur",
            "id": "367",
            "slug": "tottenham-hotspur"
        },
        "status": "Undisclosed"
    },
    {
        "date": "Aug 28",
        "player": {
            "id": "141055",
            "slug": "kevin-kampl",
            "name": "Kevin Kampl"
        },
        "fromClub": {
            "name": "Borussia Dortmund",
            "id": "124",
            "slug": "borussia-dortmund"
        },
        "toClub": {
            "name": "Bayer Leverkusen",
            "id": "131",
            "slug": "bayer-leverkusen"
        },
        "status": "Undisclosed"
    },
    {
        "date": "Aug 28",
        "player": {
            "id": "152558",
            "slug": "toni-sunjic",
            "name": "Toni Sunjic"
        },
        "fromClub": {
            "name": "Kuban Krasnodar",
            "id": "7425",
            "slug": "kuban-krasnodar"
        },
        "toClub": {
            "name": "VfB Stuttgart",
            "id": "134",
            "slug": "vfb-stuttgart"
        },
        "status": "Undisclosed"
    },
    {
        "date": "Aug 28",
        "player": {
            "id": "215792",
            "slug": "jeremy-dudziak",
            "name": "Jeremy Dudziak"
        },
        "fromClub": {
            "name": "Borussia Dortmund",
            "id": "124",
            "slug": "borussia-dortmund"
        },
        "toClub": {
            "name": "St. Pauli",
            "id": "270",
            "slug": "st-pauli"
        },
        "status": "Free"
    },
    {
        "date": "Aug 28",
        "player": {
            "id": "159543",
            "slug": "pierre-emile-højbjerg",
            "name": "Pierre-Emile Højbjerg"
        },
        "fromClub": {
            "name": "Bayern Munich",
            "id": "132",
            "slug": "bayern-munich"
        },
        "toClub": {
            "name": "Bayer Leverkusen",
            "id": "131",
            "slug": "bayer-leverkusen"
        },
        "status": "Loan"
    },
    {
        "date": "Aug 25",
        "player": {
            "id": "165552",
            "slug": "petr-jiracek",
            "name": "Petr Jiracek"
        },
        "fromClub": {
            "name": "Hamburg SV",
            "id": "127",
            "slug": "hamburg-sv"
        },
        "toClub": {
            "name": "Sparta Prague",
            "id": null,
            "slug": null
        },
        "status": "Undisclosed"
    },
    {
        "date": "Aug 25",
        "player": {
            "id": "217014",
            "slug": "felipe-pires",
            "name": "Felipe Pires"
        },
        "fromClub": {
            "name": "RB Salzburg",
            "id": "2790",
            "slug": "rb-salzburg"
        },
        "toClub": {
            "name": "TSG Hoffenheim",
            "id": "7911",
            "slug": "tsg-hoffenheim"
        },
        "status": "Undisclosed"
    },
    {
        "date": "Aug 25",
        "player": {
            "id": null,
            "slug": null,
            "name": "Seo Young-Jae"
        },
        "fromClub": {
            "name": "Hanyang University",
            "id": null,
            "slug": null
        },
        "toClub": {
            "name": "Hamburg SV",
            "id": "127",
            "slug": "hamburg-sv"
        },
        "status": "Undisclosed"
    },
    {
        "date": "Aug 25",
        "player": {
            "id": "188053",
            "slug": "kerem-demirbay",
            "name": "Kerem Demirbay"
        },
        "fromClub": {
            "name": "Hamburg SV",
            "id": "127",
            "slug": "hamburg-sv"
        },
        "toClub": {
            "name": "Fortuna Düsseldorf",
            "id": "9707",
            "slug": "fortuna-dusseldorf"
        },
        "status": "Loan"
    },
    {
        "date": "Aug 24",
        "player": {
            "id": "169773",
            "slug": "eduardo-vargas",
            "name": "Eduardo Vargas"
        },
        "fromClub": {
            "name": "Napoli",
            "id": "114",
            "slug": "napoli"
        },
        "toClub": {
            "name": "TSG Hoffenheim",
            "id": "7911",
            "slug": "tsg-hoffenheim"
        },
        "status": "Undisclosed"
    },
    {
        "date": "Aug 20",
        "player": {
            "id": "169109",
            "slug": "konstantinos-stafylidis",
            "name": "Konstantinos Stafylidis"
        },
        "fromClub": {
            "name": "Bayer Leverkusen",
            "id": "131",
            "slug": "bayer-leverkusen"
        },
        "toClub": {
            "name": "FC Augsburg",
            "id": "3841",
            "slug": "fc-augsburg"
        },
        "status": "Undisclosed"
    },
    {
        "date": "Aug 19",
        "player": {
            "id": "169438",
            "slug": "antonio-rudiger",
            "name": "Antonio Rüdiger"
        },
        "fromClub": {
            "name": "VfB Stuttgart",
            "id": "134",
            "slug": "vfb-stuttgart"
        },
        "toClub": {
            "name": "AS Roma",
            "id": "104",
            "slug": "as-roma"
        },
        "status": "Loan"
    },
    {
        "date": "Aug 18",
        "player": {
            "id": "149394",
            "slug": "nico-schulz",
            "name": "Nico Schulz"
        },
        "fromClub": {
            "name": "Hertha Berlin",
            "id": "129",
            "slug": "hertha-berlin"
        },
        "toClub": {
            "name": "Borussia Monchengladbach",
            "id": "268",
            "slug": "borussia-monchengladbach"
        },
        "status": "Undisclosed"
    },
    {
        "date": "Aug 16",
        "player": {
            "id": "174508",
            "slug": "abdul-rahman-baba",
            "name": "Abdul Rahman Baba"
        },
        "fromClub": {
            "name": "FC Augsburg",
            "id": "3841",
            "slug": "fc-augsburg"
        },
        "toClub": {
            "name": "Chelsea",
            "id": "363",
            "slug": "chelsea"
        },
        "status": "Undisclosed"
    },
    {
        "date": "Aug 14",
        "player": {
            "id": "69369",
            "slug": "gyorgy-garics",
            "name": "György Garics"
        },
        "fromClub": {
            "name": "Bologna",
            "id": "107",
            "slug": "bologna"
        },
        "toClub": {
            "name": "SV Darmstadt 98",
            "id": "3812",
            "slug": "sv-darmstadt-98"
        },
        "status": "Undisclosed"
    },
    {
        "date": "Aug 13",
        "player": {
            "id": "76778",
            "slug": "charles-aranguiz",
            "name": "Charles Aránguiz"
        },
        "fromClub": {
            "name": "Internacional",
            "id": "1936",
            "slug": "internacional"
        },
        "toClub": {
            "name": "Bayer Leverkusen",
            "id": "131",
            "slug": "bayer-leverkusen"
        },
        "status": "Undisclosed"
    },
    {
        "date": "Aug 13",
        "player": {
            "id": "113751",
            "slug": "daniel-opare",
            "name": "Daniel Opare"
        },
        "fromClub": {
            "name": "FC Porto",
            "id": "437",
            "slug": "fc-porto"
        },
        "toClub": {
            "name": "FC Augsburg",
            "id": "3841",
            "slug": "fc-augsburg"
        },
        "status": "Undisclosed"
    },
    {
        "date": "Aug 6",
        "player": {
            "id": "136434",
            "slug": "jacques-zoua",
            "name": "Jacques Zoua"
        },
        "fromClub": {
            "name": "Hamburg SV",
            "id": "127",
            "slug": "hamburg-sv"
        },
        "toClub": {
            "name": "GFC Ajaccio",
            "id": "7707",
            "slug": "gfc-ajaccio"
        },
        "status": "Undisclosed"
    },
    {
        "date": "Aug 6",
        "player": {
            "id": "46528",
            "slug": "eljero-elia",
            "name": "Eljero Elia"
        },
        "fromClub": {
            "name": "Werder Bremen",
            "id": "137",
            "slug": "werder-bremen"
        },
        "toClub": {
            "name": "Feyenoord Rotterdam",
            "id": "142",
            "slug": "feyenoord-rotterdam"
        },
        "status": "Free"
    },
    {
        "date": "Aug 5",
        "player": {
            "id": "183097",
            "slug": "aron-johannsson",
            "name": "Aron Johannsson"
        },
        "fromClub": {
            "name": "AZ Alkmaar",
            "id": "140",
            "slug": "az-alkmaar"
        },
        "toClub": {
            "name": "Werder Bremen",
            "id": "137",
            "slug": "werder-bremen"
        },
        "status": "Undisclosed"
    },
    {
        "date": "Aug 4",
        "player": {
            "id": "200856",
            "slug": "philipp-max",
            "name": "Philipp Max"
        },
        "fromClub": {
            "name": "Karlsruher SC",
            "id": "4471",
            "slug": "karlsruher-sc"
        },
        "toClub": {
            "name": "FC Augsburg",
            "id": "3841",
            "slug": "fc-augsburg"
        },
        "status": "Undisclosed"
    },
    {
        "date": "Aug 3",
        "player": {
            "id": "84893",
            "slug": "jimmy-briand",
            "name": "Jimmy Briand"
        },
        "fromClub": {
            "name": "Hannover 96",
            "id": "2428",
            "slug": "hannover-96"
        },
        "toClub": {
            "name": "Guingamp",
            "id": "171",
            "slug": "guingamp"
        },
        "status": "Undisclosed"
    },
    {
        "date": "Jul 28",
        "player": {
            "id": "102198",
            "slug": "arturo-vidal",
            "name": "Arturo Vidal"
        },
        "fromClub": {
            "name": "Juventus",
            "id": "111",
            "slug": "juventus"
        },
        "toClub": {
            "name": "Bayern Munich",
            "id": "132",
            "slug": "bayern-munich"
        },
        "status": "€ 37M"
    },
    {
        "date": "Jul 25",
        "player": {
            "id": "116366",
            "slug": "franco-di-santo",
            "name": "Franco Di Santo"
        },
        "fromClub": {
            "name": "Werder Bremen",
            "id": "137",
            "slug": "werder-bremen"
        },
        "toClub": {
            "name": "Schalke 04",
            "id": "133",
            "slug": "schalke-04"
        },
        "status": "Undisclosed"
    },
    {
        "date": "Jul 25",
        "player": {
            "id": "10639",
            "slug": "kevin-kuranyi",
            "name": "Kevin Kuranyi"
        },
        "fromClub": {
            "name": "No team",
            "id": null,
            "slug": null
        },
        "toClub": {
            "name": "TSG Hoffenheim",
            "id": "7911",
            "slug": "tsg-hoffenheim"
        },
        "status": "Free"
    },
    {
        "date": "Jul 24",
        "player": {
            "id": "33761",
            "slug": "jefferson-farfan",
            "name": "Jefferson Farfán"
        },
        "fromClub": {
            "name": "Schalke 04",
            "id": "133",
            "slug": "schalke-04"
        },
        "toClub": {
            "name": "Al-Jazira",
            "id": null,
            "slug": null
        },
        "status": "Undisclosed"
    },
    {
        "date": "Jul 24",
        "player": {
            "id": "115306",
            "slug": "sven-schipplock",
            "name": "Sven Schipplock"
        },
        "fromClub": {
            "name": "TSG Hoffenheim",
            "id": "7911",
            "slug": "tsg-hoffenheim"
        },
        "toClub": {
            "name": "Hamburg SV",
            "id": "127",
            "slug": "hamburg-sv"
        },
        "status": "Undisclosed"
    },
    {
        "date": "Jul 24",
        "player": {
            "id": "141749",
            "slug": "sandro-wieser",
            "name": "Sandro Wieser"
        },
        "fromClub": {
            "name": "TSG Hoffenheim",
            "id": "7911",
            "slug": "tsg-hoffenheim"
        },
        "toClub": {
            "name": "FC Thun",
            "id": "3024",
            "slug": "fc-thun"
        },
        "status": "Undisclosed"
    },
    {
        "date": "Jul 23",
        "player": {
            "id": "155286",
            "slug": "carlos-ascues",
            "name": "Carlos Ascues"
        },
        "fromClub": {
            "name": "Melgar",
            "id": "7312",
            "slug": "melgar"
        },
        "toClub": {
            "name": "VfL Wolfsburg",
            "id": "138",
            "slug": "vfl-wolfsburg"
        },
        "status": "Undisclosed"
    },
    {
        "date": "Jul 23",
        "player": {
            "id": "102336",
            "slug": "sascha-riether",
            "name": "Sascha Riether"
        },
        "fromClub": {
            "name": "SC Freiburg",
            "id": "126",
            "slug": "sc-freiburg"
        },
        "toClub": {
            "name": "Schalke 04",
            "id": "133",
            "slug": "schalke-04"
        },
        "status": "Undisclosed"
    },
    {
        "date": "Jul 22",
        "player": {
            "id": "160195",
            "slug": "francisco-rodriguez",
            "name": "Francisco Rodríguez"
        },
        "fromClub": {
            "name": "FC Zürich",
            "id": "3019",
            "slug": "fc-zurich"
        },
        "toClub": {
            "name": "VfL Wolfsburg",
            "id": "138",
            "slug": "vfl-wolfsburg"
        },
        "status": "Undisclosed"
    },
    {
        "date": "Jul 21",
        "player": {
            "id": "32224",
            "slug": "piotr-trochowski",
            "name": "Piotr Trochowski"
        },
        "fromClub": {
            "name": "No team",
            "id": null,
            "slug": null
        },
        "toClub": {
            "name": "FC Augsburg",
            "id": "3841",
            "slug": "fc-augsburg"
        },
        "status": "Free"
    },
    {
        "date": "Jul 18",
        "player": {
            "id": "165637",
            "slug": "vladimir-darida",
            "name": "Vladimír Darida"
        },
        "fromClub": {
            "name": "SC Freiburg",
            "id": "126",
            "slug": "sc-freiburg"
        },
        "toClub": {
            "name": "Hertha Berlin",
            "id": "129",
            "slug": "hertha-berlin"
        },
        "status": "Undisclosed"
    },
    {
        "date": "Jul 16",
        "player": {
            "id": "188052",
            "slug": "jonathan-tah",
            "name": "Jonathan Tah"
        },
        "fromClub": {
            "name": "Hamburg SV",
            "id": "127",
            "slug": "hamburg-sv"
        },
        "toClub": {
            "name": "Bayer Leverkusen",
            "id": "131",
            "slug": "bayer-leverkusen"
        },
        "status": "Undisclosed"
    },
    {
        "date": "Jul 15",
        "player": {
            "id": "84945",
            "slug": "mevlut-erdinc",
            "name": "Mevlut Erdinç"
        },
        "fromClub": {
            "name": "Saint-Etienne",
            "id": "178",
            "slug": "saint-etienne"
        },
        "toClub": {
            "name": "Hannover 96",
            "id": "2428",
            "slug": "hannover-96"
        },
        "status": "€ 3.3M"
    },
    {
        "date": "Jul 15",
        "player": {
            "id": "172151",
            "slug": "zhang-xizhe",
            "name": "Zhang Xizhe"
        },
        "fromClub": {
            "name": "VfL Wolfsburg",
            "id": "138",
            "slug": "vfl-wolfsburg"
        },
        "toClub": {
            "name": "Beijing Guoan",
            "id": null,
            "slug": null
        },
        "status": "Free"
    },
    {
        "date": "Jul 15",
        "player": {
            "id": "132063",
            "slug": "luca-caldirola",
            "name": "Luca Caldirola"
        },
        "fromClub": {
            "name": "Werder Bremen",
            "id": "137",
            "slug": "werder-bremen"
        },
        "toClub": {
            "name": "SV Darmstadt 98",
            "id": "3812",
            "slug": "sv-darmstadt-98"
        },
        "status": "Loan"
    },
    {
        "date": "Jul 13",
        "player": {
            "id": "130123",
            "slug": "ciro-immobile",
            "name": "Ciro Immobile"
        },
        "fromClub": {
            "name": "Borussia Dortmund",
            "id": "124",
            "slug": "borussia-dortmund"
        },
        "toClub": {
            "name": "Sevilla",
            "id": "243",
            "slug": "sevilla"
        },
        "status": "Undisclosed"
    },
    {
        "date": "Jul 13",
        "player": {
            "id": "27014",
            "slug": "bastian-schweinsteiger",
            "name": "Bastian Schweinsteiger"
        },
        "fromClub": {
            "name": "Bayern Munich",
            "id": "132",
            "slug": "bayern-munich"
        },
        "toClub": {
            "name": "Manchester United",
            "id": "360",
            "slug": "manchester-united"
        },
        "status": "Undisclosed"
    },
    {
        "date": "Jul 11",
        "player": {
            "id": "68069",
            "slug": "valon-behrami",
            "name": "Valon Behrami"
        },
        "fromClub": {
            "name": "Hamburg SV",
            "id": "127",
            "slug": "hamburg-sv"
        },
        "toClub": {
            "name": "Watford",
            "id": "395",
            "slug": "watford"
        },
        "status": "Undisclosed"
    },
    {
        "date": "Jul 11",
        "player": {
            "id": "95818",
            "slug": "emiliano-insua",
            "name": "Emiliano Insúa"
        },
        "fromClub": {
            "name": "Atlético Madrid",
            "id": "1068",
            "slug": "atletico-madrid"
        },
        "toClub": {
            "name": "VfB Stuttgart",
            "id": "134",
            "slug": "vfb-stuttgart"
        },
        "status": "Undisclosed"
    },
    {
        "date": "Jul 10",
        "player": {
            "id": "186430",
            "slug": "andreas-christensen",
            "name": "Andreas Christensen"
        },
        "fromClub": {
            "name": "Chelsea",
            "id": "363",
            "slug": "chelsea"
        },
        "toClub": {
            "name": "Borussia Monchengladbach",
            "id": "268",
            "slug": "borussia-monchengladbach"
        },
        "status": "Loan"
    },
    {
        "date": "Jul 8",
        "player": {
            "id": "122280",
            "slug": "kevin-trapp",
            "name": "Kevin Trapp"
        },
        "fromClub": {
            "name": "Eintracht Frankfurt",
            "id": "125",
            "slug": "eintracht-frankfurt"
        },
        "toClub": {
            "name": "Paris Saint-Germain",
            "id": "160",
            "slug": "paris-saint-germain"
        },
        "status": "Undisclosed"
    },
    {
        "date": "Jul 5",
        "player": {
            "id": "178607",
            "slug": "milos-jojic",
            "name": "Milos Jojic"
        },
        "fromClub": {
            "name": "Borussia Dortmund",
            "id": "124",
            "slug": "borussia-dortmund"
        },
        "toClub": {
            "name": "FC Cologne",
            "id": "122",
            "slug": "fc-cologne"
        },
        "status": "Undisclosed"
    },
    {
        "date": "Jul 5",
        "player": {
            "id": "33234",
            "slug": "emir-spahic",
            "name": "Emir Spahic"
        },
        "fromClub": {
            "name": "No team",
            "id": null,
            "slug": null
        },
        "toClub": {
            "name": "Hamburg SV",
            "id": "127",
            "slug": "hamburg-sv"
        },
        "status": "Free"
    },
    {
        "date": "Jul 3",
        "player": {
            "id": "205910",
            "slug": "alexander-brunst-zollner",
            "name": "Alexander Brunst-Zöllner"
        },
        "fromClub": {
            "name": "Hamburg SV",
            "id": "127",
            "slug": "hamburg-sv"
        },
        "toClub": {
            "name": "VfL Wolfsburg",
            "id": "138",
            "slug": "vfl-wolfsburg"
        },
        "status": "Undisclosed"
    },
    {
        "date": "Jul 2",
        "player": {
            "id": "42904",
            "slug": "david-abraham",
            "name": "David Abraham"
        },
        "fromClub": {
            "name": "TSG Hoffenheim",
            "id": "7911",
            "slug": "tsg-hoffenheim"
        },
        "toClub": {
            "name": "Eintracht Frankfurt",
            "id": "125",
            "slug": "eintracht-frankfurt"
        },
        "status": "Undisclosed"
    },
    {
        "date": "Jul 2",
        "player": {
            "id": "136593",
            "slug": "sebastian-polter",
            "name": "Sebastian Polter"
        },
        "fromClub": {
            "name": "Mainz",
            "id": "2950",
            "slug": "mainz"
        },
        "toClub": {
            "name": "Queens Park Rangers",
            "id": "334",
            "slug": "queens-park-rangers"
        },
        "status": "Undisclosed"
    },
    {
        "date": "Jul 1",
        "player": {
            "id": "127502",
            "slug": "douglas-costa",
            "name": "Douglas Costa"
        },
        "fromClub": {
            "name": "Shakhtar Donetsk",
            "id": null,
            "slug": null
        },
        "toClub": {
            "name": "Bayern Munich",
            "id": "132",
            "slug": "bayern-munich"
        },
        "status": "€ 30M"
    },
    {
        "date": "Jul 1",
        "player": {
            "id": "52644",
            "slug": "gonzalo-castro",
            "name": "Gonzalo Castro"
        },
        "fromClub": {
            "name": "Bayer Leverkusen",
            "id": "131",
            "slug": "bayer-leverkusen"
        },
        "toClub": {
            "name": "Borussia Dortmund",
            "id": "124",
            "slug": "borussia-dortmund"
        },
        "status": "€ 11M"
    },
    {
        "date": "Jul 1",
        "player": {
            "id": "134939",
            "slug": "joselu",
            "name": "Joselu"
        },
        "fromClub": {
            "name": "Hannover 96",
            "id": "2428",
            "slug": "hannover-96"
        },
        "toClub": {
            "name": "Stoke City",
            "id": "336",
            "slug": "stoke-city"
        },
        "status": "€ 8M"
    },
    {
        "date": "Jul 1",
        "player": {
            "id": "202232",
            "slug": "joelinton",
            "name": "Joelinton"
        },
        "fromClub": {
            "name": "Sport",
            "id": "7635",
            "slug": "sport"
        },
        "toClub": {
            "name": "TSG Hoffenheim",
            "id": "7911",
            "slug": "tsg-hoffenheim"
        },
        "status": "Undisclosed"
    },
    {
        "date": "Jul 1",
        "player": {
            "id": "99581",
            "slug": "robert-almer",
            "name": "Robert Almer"
        },
        "fromClub": {
            "name": "Hannover 96",
            "id": "2428",
            "slug": "hannover-96"
        },
        "toClub": {
            "name": "Austria Vienna",
            "id": "1382",
            "slug": "austria-vienna"
        },
        "status": "Undisclosed"
    },
    {
        "date": "Jul 1",
        "player": {
            "id": "174515",
            "slug": "zlatan-alomerovic",
            "name": "Zlatan Alomerovic"
        },
        "fromClub": {
            "name": "Borussia Dortmund",
            "id": "124",
            "slug": "borussia-dortmund"
        },
        "toClub": {
            "name": "Kaiserslautern",
            "id": "130",
            "slug": "kaiserslautern"
        },
        "status": "Undisclosed"
    },
    {
        "date": "Jul 1",
        "player": {
            "id": null,
            "slug": null,
            "name": "Batuhan Altintas"
        },
        "fromClub": {
            "name": "Bursaspor",
            "id": "3837",
            "slug": "bursaspor"
        },
        "toClub": {
            "name": "Hamburg SV",
            "id": "127",
            "slug": "hamburg-sv"
        },
        "status": "Undisclosed"
    },
    {
        "date": "Jul 1",
        "player": {
            "id": "122797",
            "slug": "charlison-benschop",
            "name": "Charlison Benschop"
        },
        "fromClub": {
            "name": "Fortuna Düsseldorf",
            "id": "9707",
            "slug": "fortuna-dusseldorf"
        },
        "toClub": {
            "name": "Hannover 96",
            "id": "2428",
            "slug": "hannover-96"
        },
        "status": "Undisclosed"
    },
    {
        "date": "Jul 1",
        "player": {
            "id": "164896",
            "slug": "junior-caicara",
            "name": "Júnior Caiçara"
        },
        "fromClub": {
            "name": "Ludogorets Razgrad ",
            "id": null,
            "slug": null
        },
        "toClub": {
            "name": "Schalke 04",
            "id": "133",
            "slug": "schalke-04"
        },
        "status": "Undisclosed"
    },
    {
        "date": "Jul 1",
        "player": {
            "id": "212237",
            "slug": "nico-elvedi",
            "name": "Nico Elvedi"
        },
        "fromClub": {
            "name": "FC Zürich",
            "id": "3019",
            "slug": "fc-zurich"
        },
        "toClub": {
            "name": "Borussia Monchengladbach",
            "id": "268",
            "slug": "borussia-monchengladbach"
        },
        "status": "Undisclosed"
    },
    {
        "date": "Jul 1",
        "player": {
            "id": "147234",
            "slug": "roberto-firmino",
            "name": "Roberto Firmino"
        },
        "fromClub": {
            "name": "TSG Hoffenheim",
            "id": "7911",
            "slug": "tsg-hoffenheim"
        },
        "toClub": {
            "name": "Liverpool",
            "id": "364",
            "slug": "liverpool"
        },
        "status": "Undisclosed"
    },
    {
        "date": "Jul 1",
        "player": {
            "id": "105140",
            "slug": "fabian-frei",
            "name": "Fabian Frei"
        },
        "fromClub": {
            "name": "FC Basel",
            "id": "989",
            "slug": "fc-basel"
        },
        "toClub": {
            "name": "Mainz",
            "id": "2950",
            "slug": "mainz"
        },
        "status": "Undisclosed"
    },
    {
        "date": "Jul 1",
        "player": {
            "id": "153488",
            "slug": "johannes-geis",
            "name": "Johannes Geis"
        },
        "fromClub": {
            "name": "Mainz",
            "id": "2950",
            "slug": "mainz"
        },
        "toClub": {
            "name": "Schalke 04",
            "id": "133",
            "slug": "schalke-04"
        },
        "status": "Undisclosed"
    },
    {
        "date": "Jul 1",
        "player": {
            "id": "146804",
            "slug": "michael-gregoritsch",
            "name": "Michael Gregoritsch"
        },
        "fromClub": {
            "name": "TSG Hoffenheim",
            "id": "7911",
            "slug": "tsg-hoffenheim"
        },
        "toClub": {
            "name": "VfL Bochum",
            "id": "121",
            "slug": "vfl-bochum"
        },
        "status": "Undisclosed"
    },
    {
        "date": "Jul 1",
        "player": {
            "id": "179571",
            "slug": "vincenzo-grifo",
            "name": "Vincenzo Grifo"
        },
        "fromClub": {
            "name": "TSG Hoffenheim",
            "id": "7911",
            "slug": "tsg-hoffenheim"
        },
        "toClub": {
            "name": "SC Freiburg",
            "id": "126",
            "slug": "sc-freiburg"
        },
        "status": "Undisclosed"
    },
    {
        "date": "Jul 1",
        "player": {
            "id": "158066",
            "slug": "thorgan-hazard",
            "name": "Thorgan Hazard"
        },
        "fromClub": {
            "name": "Chelsea",
            "id": "363",
            "slug": "chelsea"
        },
        "toClub": {
            "name": "Borussia Monchengladbach",
            "id": "268",
            "slug": "borussia-monchengladbach"
        },
        "status": "Undisclosed"
    },
    {
        "date": "Jul 1",
        "player": {
            "id": "167683",
            "slug": "dominique-heintz",
            "name": "Dominique Heintz"
        },
        "fromClub": {
            "name": "Kaiserslautern",
            "id": "130",
            "slug": "kaiserslautern"
        },
        "toClub": {
            "name": "FC Cologne",
            "id": "122",
            "slug": "fc-cologne"
        },
        "status": "Undisclosed"
    },
    {
        "date": "Jul 1",
        "player": {
            "id": "174442",
            "slug": "philip-heise",
            "name": "Philip Heise"
        },
        "fromClub": {
            "name": "1. FC Heidenheim 1846",
            "id": "6418",
            "slug": "1-fc-heidenheim-1846"
        },
        "toClub": {
            "name": "VfB Stuttgart",
            "id": "134",
            "slug": "vfb-stuttgart"
        },
        "status": "Undisclosed"
    },
    {
        "date": "Jul 1",
        "player": {
            "id": "122289",
            "slug": "lewis-holtby",
            "name": "Lewis Holtby"
        },
        "fromClub": {
            "name": "Tottenham Hotspur",
            "id": "367",
            "slug": "tottenham-hotspur"
        },
        "toClub": {
            "name": "Hamburg SV",
            "id": "127",
            "slug": "hamburg-sv"
        },
        "status": "Undisclosed"
    },
    {
        "date": "Jul 1",
        "player": {
            "id": "151715",
            "slug": "pavel-kaderabek",
            "name": "Pavel Kaderabek"
        },
        "fromClub": {
            "name": "Sparta Prague",
            "id": null,
            "slug": null
        },
        "toClub": {
            "name": "TSG Hoffenheim",
            "id": "7911",
            "slug": "tsg-hoffenheim"
        },
        "status": "Undisclosed"
    },
    {
        "date": "Jul 1",
        "player": {
            "id": "153489",
            "slug": "felix-klaus",
            "name": "Felix Klaus"
        },
        "fromClub": {
            "name": "SC Freiburg",
            "id": "126",
            "slug": "sc-freiburg"
        },
        "toClub": {
            "name": "Hannover 96",
            "id": "2428",
            "slug": "hannover-96"
        },
        "status": "Undisclosed"
    },
    {
        "date": "Jul 1",
        "player": {
            "id": "220193",
            "slug": "jan-kliment",
            "name": "Jan Kliment"
        },
        "fromClub": {
            "name": "FC Vysocina Jihlava ",
            "id": null,
            "slug": null
        },
        "toClub": {
            "name": "VfB Stuttgart",
            "id": "134",
            "slug": "vfb-stuttgart"
        },
        "status": "Undisclosed"
    },
    {
        "date": "Jul 1",
        "player": {
            "id": "139644",
            "slug": "julian-koch",
            "name": "Julian Koch"
        },
        "fromClub": {
            "name": "Mainz",
            "id": "2950",
            "slug": "mainz"
        },
        "toClub": {
            "name": "Fortuna Düsseldorf",
            "id": "9707",
            "slug": "fortuna-dusseldorf"
        },
        "status": "Undisclosed"
    },
    {
        "date": "Jul 1",
        "player": {
            "id": "110846",
            "slug": "max-kruse",
            "name": "Max Kruse"
        },
        "fromClub": {
            "name": "Borussia Monchengladbach",
            "id": "268",
            "slug": "borussia-monchengladbach"
        },
        "toClub": {
            "name": "VfL Wolfsburg",
            "id": "138",
            "slug": "vfl-wolfsburg"
        },
        "status": "Undisclosed"
    },
    {
        "date": "Jul 1",
        "player": {
            "id": "123190",
            "slug": "stefan-kutschke",
            "name": "Stefan Kutschke"
        },
        "fromClub": {
            "name": "VfL Wolfsburg",
            "id": "138",
            "slug": "vfl-wolfsburg"
        },
        "toClub": {
            "name": "1. FC Nürnberg",
            "id": "269",
            "slug": "1-fc-nurnberg"
        },
        "status": "Undisclosed"
    },
    {
        "date": "Jul 1",
        "player": {
            "id": "107540",
            "slug": "mitch-langerak",
            "name": "Mitch Langerak"
        },
        "fromClub": {
            "name": "Borussia Dortmund",
            "id": "124",
            "slug": "borussia-dortmund"
        },
        "toClub": {
            "name": "VfB Stuttgart",
            "id": "134",
            "slug": "vfb-stuttgart"
        },
        "status": "Undisclosed"
    },
    {
        "date": "Jul 1",
        "player": {
            "id": "179359",
            "slug": "arkadiusz-milik",
            "name": "Arkadiusz Milik"
        },
        "fromClub": {
            "name": "Bayer Leverkusen",
            "id": "131",
            "slug": "bayer-leverkusen"
        },
        "toClub": {
            "name": "Ajax Amsterdam",
            "id": "139",
            "slug": "ajax-amsterdam"
        },
        "status": "Undisclosed"
    },
    {
        "date": "Jul 1",
        "player": {
            "id": "202090",
            "slug": "yoshinori-muto",
            "name": "Yoshinori Muto"
        },
        "fromClub": {
            "name": "FC Tokyo",
            "id": "3384",
            "slug": "fc-tokyo"
        },
        "toClub": {
            "name": "Mainz",
            "id": "2950",
            "slug": "mainz"
        },
        "status": "Undisclosed"
    },
    {
        "date": "Jul 1",
        "player": {
            "id": "151765",
            "slug": "matija-nastasic",
            "name": "Matija Nastasic"
        },
        "fromClub": {
            "name": "Manchester City",
            "id": "382",
            "slug": "manchester-city"
        },
        "toClub": {
            "name": "Schalke 04",
            "id": "133",
            "slug": "schalke-04"
        },
        "status": "Undisclosed"
    },
    {
        "date": "Jul 1",
        "player": {
            "id": "162096",
            "slug": "florian-niederlechner",
            "name": "Florian Niederlechner"
        },
        "fromClub": {
            "name": "1. FC Heidenheim 1846",
            "id": "6418",
            "slug": "1-fc-heidenheim-1846"
        },
        "toClub": {
            "name": "Mainz",
            "id": "2950",
            "slug": "mainz"
        },
        "status": "Undisclosed"
    },
    {
        "date": "Jul 1",
        "player": {
            "id": "112544",
            "slug": "kyriakos-papadopoulos",
            "name": "Kyriakos Papadopoulos"
        },
        "fromClub": {
            "name": "Schalke 04",
            "id": "133",
            "slug": "schalke-04"
        },
        "toClub": {
            "name": "Bayer Leverkusen",
            "id": "131",
            "slug": "bayer-leverkusen"
        },
        "status": "Undisclosed"
    },
    {
        "date": "Jul 1",
        "player": {
            "id": "12910",
            "slug": "pepe-reina",
            "name": "Pepe Reina"
        },
        "fromClub": {
            "name": "Bayern Munich",
            "id": "132",
            "slug": "bayern-munich"
        },
        "toClub": {
            "name": "Napoli",
            "id": "114",
            "slug": "napoli"
        },
        "status": "Undisclosed"
    },
    {
        "date": "Jul 1",
        "player": {
            "id": "122399",
            "slug": "sercan-sararer",
            "name": "Sercan Sararer"
        },
        "fromClub": {
            "name": "VfB Stuttgart",
            "id": "134",
            "slug": "vfb-stuttgart"
        },
        "toClub": {
            "name": "Fortuna Düsseldorf",
            "id": "9707",
            "slug": "fortuna-dusseldorf"
        },
        "status": "Undisclosed"
    },
    {
        "date": "Jul 1",
        "player": {
            "id": "153290",
            "slug": "jonathan-schmid",
            "name": "Jonathan Schmid"
        },
        "fromClub": {
            "name": "SC Freiburg",
            "id": "126",
            "slug": "sc-freiburg"
        },
        "toClub": {
            "name": "TSG Hoffenheim",
            "id": "7911",
            "slug": "tsg-hoffenheim"
        },
        "status": "Undisclosed"
    },
    {
        "date": "Jul 1",
        "player": {
            "id": "179233",
            "slug": "fabian-schar",
            "name": "Fabian Schär"
        },
        "fromClub": {
            "name": "FC Basel",
            "id": "989",
            "slug": "fc-basel"
        },
        "toClub": {
            "name": "TSG Hoffenheim",
            "id": "7911",
            "slug": "tsg-hoffenheim"
        },
        "status": "Undisclosed"
    },
    {
        "date": "Jul 1",
        "player": {
            "id": "196032",
            "slug": "davie-selke",
            "name": "Davie Selke"
        },
        "fromClub": {
            "name": "Werder Bremen",
            "id": "137",
            "slug": "werder-bremen"
        },
        "toClub": {
            "name": "RB Leipzig",
            "id": "11420",
            "slug": "rb-leipzig"
        },
        "status": "Undisclosed"
    },
    {
        "date": "Jul 1",
        "player": {
            "id": "136775",
            "slug": "xherdan-shaqiri",
            "name": "Xherdan Shaqiri"
        },
        "fromClub": {
            "name": "Bayern Munich",
            "id": "132",
            "slug": "bayern-munich"
        },
        "toClub": {
            "name": "Internazionale",
            "id": "110",
            "slug": "internazionale"
        },
        "status": "Undisclosed"
    },
    {
        "date": "Jul 1",
        "player": {
            "id": "170193",
            "slug": "oliver-sorg",
            "name": "Oliver Sorg"
        },
        "fromClub": {
            "name": "SC Freiburg",
            "id": "126",
            "slug": "sc-freiburg"
        },
        "toClub": {
            "name": "Hannover 96",
            "id": "2428",
            "slug": "hannover-96"
        },
        "status": "Undisclosed"
    },
    {
        "date": "Jul 1",
        "player": {
            "id": "117278",
            "slug": "lars-stindl",
            "name": "Lars Stindl"
        },
        "fromClub": {
            "name": "Hannover 96",
            "id": "2428",
            "slug": "hannover-96"
        },
        "toClub": {
            "name": "Borussia Monchengladbach",
            "id": "268",
            "slug": "borussia-monchengladbach"
        },
        "status": "Undisclosed"
    },
    {
        "date": "Jul 1",
        "player": {
            "id": "149280",
            "slug": "maxi-thiel",
            "name": "Maxi Thiel"
        },
        "fromClub": {
            "name": "FC Cologne",
            "id": "122",
            "slug": "fc-cologne"
        },
        "toClub": {
            "name": "1. FC Union Berlin",
            "id": "598",
            "slug": "1-fc-union-berlin"
        },
        "status": "Undisclosed"
    },
    {
        "date": "Jul 1",
        "player": {
            "id": "125136",
            "slug": "przemyslaw-tyton",
            "name": "Przemyslaw Tyton"
        },
        "fromClub": {
            "name": "PSV Eindhoven",
            "id": "148",
            "slug": "psv-eindhoven"
        },
        "toClub": {
            "name": "VfB Stuttgart",
            "id": "134",
            "slug": "vfb-stuttgart"
        },
        "status": "Undisclosed"
    },
    {
        "date": "Jul 1",
        "player": {
            "id": "145953",
            "slug": "anthony-ujah",
            "name": "Anthony Ujah"
        },
        "fromClub": {
            "name": "FC Cologne",
            "id": "122",
            "slug": "fc-cologne"
        },
        "toClub": {
            "name": "Werder Bremen",
            "id": "137",
            "slug": "werder-bremen"
        },
        "status": "Undisclosed"
    },
    {
        "date": "Jul 1",
        "player": {
            "id": "113733",
            "slug": "sven-ulreich",
            "name": "Sven Ulreich"
        },
        "fromClub": {
            "name": "VfB Stuttgart",
            "id": "134",
            "slug": "vfb-stuttgart"
        },
        "toClub": {
            "name": "Bayern Munich",
            "id": "132",
            "slug": "bayern-munich"
        },
        "status": "Undisclosed"
    },
    {
        "date": "Jul 1",
        "player": {
            "id": "200192",
            "slug": "julian-weigl",
            "name": "Julian Weigl"
        },
        "fromClub": {
            "name": "TSV 1860 Munich",
            "id": "135",
            "slug": "tsv-1860-munich"
        },
        "toClub": {
            "name": "Borussia Dortmund",
            "id": "124",
            "slug": "borussia-dortmund"
        },
        "status": "Undisclosed"
    },
    {
        "date": "Jul 1",
        "player": {
            "id": "174526",
            "slug": "kevin-wimmer",
            "name": "Kevin Wimmer"
        },
        "fromClub": {
            "name": "FC Cologne",
            "id": "122",
            "slug": "fc-cologne"
        },
        "toClub": {
            "name": "Tottenham Hotspur",
            "id": "367",
            "slug": "tottenham-hotspur"
        },
        "status": "Undisclosed"
    },
    {
        "date": "Jul 1",
        "player": {
            "id": "144752",
            "slug": "philipp-wollscheid",
            "name": "Philipp Wollscheid"
        },
        "fromClub": {
            "name": "Bayer Leverkusen",
            "id": "131",
            "slug": "bayer-leverkusen"
        },
        "toClub": {
            "name": "Stoke City",
            "id": "336",
            "slug": "stoke-city"
        },
        "status": "Undisclosed"
    },
    {
        "date": "Jul 1",
        "player": {
            "id": null,
            "slug": null,
            "name": "Mandela Egbo"
        },
        "fromClub": {
            "name": "Crystal Palace",
            "id": "384",
            "slug": "crystal-palace"
        },
        "toClub": {
            "name": "Borussia Monchengladbach",
            "id": "268",
            "slug": "borussia-monchengladbach"
        },
        "status": "Free"
    },
    {
        "date": "Jul 1",
        "player": {
            "id": "37323",
            "slug": "christian-fuchs",
            "name": "Christian Fuchs"
        },
        "fromClub": {
            "name": "Schalke 04",
            "id": "133",
            "slug": "schalke-04"
        },
        "toClub": {
            "name": "Leicester City",
            "id": "375",
            "slug": "leicester-city"
        },
        "status": "Free"
    },
    {
        "date": "Jul 1",
        "player": {
            "id": null,
            "slug": null,
            "name": "Ulisses Garcia"
        },
        "fromClub": {
            "name": "Grasshoppers",
            "id": "492",
            "slug": "grasshoppers"
        },
        "toClub": {
            "name": "Werder Bremen",
            "id": "137",
            "slug": "werder-bremen"
        },
        "status": "Free"
    },
    {
        "date": "Jul 1",
        "player": {
            "id": "10004",
            "slug": "johnny-heitinga",
            "name": "Johnny Heitinga"
        },
        "fromClub": {
            "name": "Hertha Berlin",
            "id": "129",
            "slug": "hertha-berlin"
        },
        "toClub": {
            "name": "Ajax Amsterdam",
            "id": "139",
            "slug": "ajax-amsterdam"
        },
        "status": "Free"
    },
    {
        "date": "Jul 1",
        "player": {
            "id": "190161",
            "slug": "joshua-kimmich",
            "name": "Joshua Kimmich"
        },
        "fromClub": {
            "name": "VfB Stuttgart",
            "id": "134",
            "slug": "vfb-stuttgart"
        },
        "toClub": {
            "name": "Bayern Munich",
            "id": "132",
            "slug": "bayern-munich"
        },
        "status": "Free"
    },
    {
        "date": "Jul 1",
        "player": {
            "id": "121011",
            "slug": "danny-latza",
            "name": "Danny Latza"
        },
        "fromClub": {
            "name": "VfL Bochum",
            "id": "121",
            "slug": "vfl-bochum"
        },
        "toClub": {
            "name": "Mainz",
            "id": "2950",
            "slug": "mainz"
        },
        "status": "Free"
    },
    {
        "date": "Jul 1",
        "player": {
            "id": "121562",
            "slug": "sebastian-prodl",
            "name": "Sebastian Prödl"
        },
        "fromClub": {
            "name": "Werder Bremen",
            "id": "137",
            "slug": "werder-bremen"
        },
        "toClub": {
            "name": "Watford",
            "id": "395",
            "slug": "watford"
        },
        "status": "Free"
    },
    {
        "date": "Jul 1",
        "player": {
            "id": "194090",
            "slug": "andre-ramalho",
            "name": "André Ramalho"
        },
        "fromClub": {
            "name": "RB Leipzig",
            "id": "11420",
            "slug": "rb-leipzig"
        },
        "toClub": {
            "name": "Bayer Leverkusen",
            "id": "131",
            "slug": "bayer-leverkusen"
        },
        "status": "Free"
    },
    {
        "date": "Jul 1",
        "player": {
            "id": "111224",
            "slug": "stefan-reinartz",
            "name": "Stefan Reinartz"
        },
        "fromClub": {
            "name": "Bayer Leverkusen",
            "id": "131",
            "slug": "bayer-leverkusen"
        },
        "toClub": {
            "name": "Eintracht Frankfurt",
            "id": "125",
            "slug": "eintracht-frankfurt"
        },
        "status": "Free"
    },
    {
        "date": "Jul 1",
        "player": {
            "id": "122273",
            "slug": "tobias-sippel",
            "name": "Tobias Sippel"
        },
        "fromClub": {
            "name": "Kaiserslautern",
            "id": "130",
            "slug": "kaiserslautern"
        },
        "toClub": {
            "name": "Borussia Monchengladbach",
            "id": "268",
            "slug": "borussia-monchengladbach"
        },
        "status": "Free"
    },
    {
        "date": "Jul 1",
        "player": {
            "id": "43498",
            "slug": "philipp-tschauner",
            "name": "Philipp Tschauner"
        },
        "fromClub": {
            "name": "St. Pauli",
            "id": "270",
            "slug": "st-pauli"
        },
        "toClub": {
            "name": "Hannover 96",
            "id": "2428",
            "slug": "hannover-96"
        },
        "status": "Free"
    },
    {
        "date": "Jul 1",
        "player": {
            "id": "159139",
            "slug": "mitchell-weiser",
            "name": "Mitchell Weiser"
        },
        "fromClub": {
            "name": "Bayern Munich",
            "id": "132",
            "slug": "bayern-munich"
        },
        "toClub": {
            "name": "Hertha Berlin",
            "id": "129",
            "slug": "hertha-berlin"
        },
        "status": "Free"
    },
    {
        "date": "Jul 1",
        "player": {
            "id": "136598",
            "slug": "felix-wiedwald",
            "name": "Felix Wiedwald"
        },
        "fromClub": {
            "name": "Eintracht Frankfurt",
            "id": "125",
            "slug": "eintracht-frankfurt"
        },
        "toClub": {
            "name": "Werder Bremen",
            "id": "137",
            "slug": "werder-bremen"
        },
        "status": "Free"
    },
    {
        "date": "Jul 1",
        "player": {
            "id": "167376",
            "slug": "philipp-hosiner",
            "name": "Philipp Hosiner"
        },
        "fromClub": {
            "name": "Stade Rennais",
            "id": "169",
            "slug": "stade-rennais"
        },
        "toClub": {
            "name": "FC Cologne",
            "id": "122",
            "slug": "fc-cologne"
        },
        "status": "Loan"
    },
    {
        "date": "Jul 1",
        "player": {
            "id": "182424",
            "slug": "timon-wellenreuther",
            "name": "Timon Wellenreuther"
        },
        "fromClub": {
            "name": "Schalke 04",
            "id": "133",
            "slug": "schalke-04"
        },
        "toClub": {
            "name": "Mallorca",
            "id": "84",
            "slug": "mallorca"
        },
        "status": "Loan"
    },
    {
        "date": "Jun 24",
        "player": {
            "id": "139948",
            "slug": "lukas-rupp",
            "name": "Lukas Rupp"
        },
        "fromClub": {
            "name": "SC Paderborn 07",
            "id": "3307",
            "slug": "sc-paderborn-07"
        },
        "toClub": {
            "name": "VfB Stuttgart",
            "id": "134",
            "slug": "vfb-stuttgart"
        },
        "status": "Undisclosed"
    },
    {
        "date": "Jun 18",
        "player": {
            "id": "32890",
            "slug": "dario-kresic",
            "name": "Dario Kresic"
        },
        "fromClub": {
            "name": "Bayer Leverkusen",
            "id": "131",
            "slug": "bayer-leverkusen"
        },
        "toClub": {
            "name": "Borussia Monchengladbach",
            "id": "268",
            "slug": "borussia-monchengladbach"
        },
        "status": "Undisclosed"
    },
    {
        "date": "Jun 14",
        "player": {
            "id": "175906",
            "slug": "roman-burki",
            "name": "Roman Bürki"
        },
        "fromClub": {
            "name": "SC Freiburg",
            "id": "126",
            "slug": "sc-freiburg"
        },
        "toClub": {
            "name": "Borussia Dortmund",
            "id": "124",
            "slug": "borussia-dortmund"
        },
        "status": "Undisclosed"
    },
    {
        "date": "Jun 11",
        "player": {
            "id": "121255",
            "slug": "admir-mehmedi",
            "name": "Admir Mehmedi"
        },
        "fromClub": {
            "name": "SC Freiburg",
            "id": "126",
            "slug": "sc-freiburg"
        },
        "toClub": {
            "name": "Bayer Leverkusen",
            "id": "131",
            "slug": "bayer-leverkusen"
        },
        "status": "Undisclosed"
    },
    {
        "date": "Feb 2",
        "player": {
            "id": "183268",
            "slug": "serey-die",
            "name": "Serey Dié"
        },
        "fromClub": {
            "name": "FC Basel",
            "id": "989",
            "slug": "fc-basel"
        },
        "toClub": {
            "name": "VfB Stuttgart",
            "id": "134",
            "slug": "vfb-stuttgart"
        },
        "status": "Undisclosed"
    },
    {
        "date": "Feb 2",
        "player": {
            "id": "168514",
            "slug": "marcelo-diaz",
            "name": "Marcelo Díaz"
        },
        "fromClub": {
            "name": "FC Basel",
            "id": "989",
            "slug": "fc-basel"
        },
        "toClub": {
            "name": "Hamburg SV",
            "id": "127",
            "slug": "hamburg-sv"
        },
        "status": "Undisclosed"
    },
    {
        "date": "Feb 2",
        "player": {
            "id": "136580",
            "slug": "andre-schurrle",
            "name": "André Schürrle"
        },
        "fromClub": {
            "name": "Chelsea",
            "id": "363",
            "slug": "chelsea"
        },
        "toClub": {
            "name": "VfL Wolfsburg",
            "id": "138",
            "slug": "vfl-wolfsburg"
        },
        "status": "Undisclosed"
    },
    {
        "date": "Feb 2",
        "player": {
            "id": "192710",
            "slug": "deyverson",
            "name": "Deyverson"
        },
        "fromClub": {
            "name": "Belenenses",
            "id": "3519",
            "slug": "belenenses"
        },
        "toClub": {
            "name": "FC Cologne",
            "id": "122",
            "slug": "fc-cologne"
        },
        "status": "Loan"
    },
    {
        "date": "Feb 2",
        "player": {
            "id": "205660",
            "slug": "oliver-husing",
            "name": "Oliver Hüsing"
        },
        "fromClub": {
            "name": "Werder Bremen",
            "id": "137",
            "slug": "werder-bremen"
        },
        "toClub": {
            "name": "Hansa Rostock",
            "id": null,
            "slug": null
        },
        "status": "Loan"
    },
    {
        "date": "Feb 2",
        "player": {
            "id": "85194",
            "slug": "jan-rosenthal",
            "name": "Jan Rosenthal"
        },
        "fromClub": {
            "name": "Eintracht Frankfurt",
            "id": "125",
            "slug": "eintracht-frankfurt"
        },
        "toClub": {
            "name": "Darmstadt",
            "id": "7034",
            "slug": "darmstadt"
        },
        "status": "Loan"
    },
    {
        "date": "Jan 30",
        "player": {
            "id": "69737",
            "slug": "pedro-geromel",
            "name": "Pedro Geromel"
        },
        "fromClub": {
            "name": "FC Cologne",
            "id": "122",
            "slug": "fc-cologne"
        },
        "toClub": {
            "name": "Grêmio",
            "id": "6273",
            "slug": "gremio"
        },
        "status": "Undisclosed"
    },
    {
        "date": "Jan 30",
        "player": {
            "id": "85175",
            "slug": "srdjan-lakic",
            "name": "Srdjan Lakic"
        },
        "fromClub": {
            "name": "Kaiserslautern",
            "id": "130",
            "slug": "kaiserslautern"
        },
        "toClub": {
            "name": "SC Paderborn 07",
            "id": "3307",
            "slug": "sc-paderborn-07"
        },
        "status": "Undisclosed"
    },
    {
        "date": "Jan 30",
        "player": {
            "id": "89421",
            "slug": "martin-lanig",
            "name": "Martin Lanig"
        },
        "fromClub": {
            "name": "Eintracht Frankfurt",
            "id": "125",
            "slug": "eintracht-frankfurt"
        },
        "toClub": {
            "name": "APOEL Nicosia",
            "id": null,
            "slug": null
        },
        "status": "Undisclosed"
    },
    {
        "date": "Jan 30",
        "player": {
            "id": "190674",
            "slug": "viktor-maier",
            "name": "Viktor Maier"
        },
        "fromClub": {
            "name": "SC Paderborn 07",
            "id": "3307",
            "slug": "sc-paderborn-07"
        },
        "toClub": {
            "name": "Alemannia Aachen",
            "id": null,
            "slug": null
        },
        "status": "Undisclosed"
    },
    {
        "date": "Jan 30",
        "player": {
            "id": "113217",
            "slug": "adrian-nikci",
            "name": "Adrian Nikci"
        },
        "fromClub": {
            "name": "Hannover 96",
            "id": "2428",
            "slug": "hannover-96"
        },
        "toClub": {
            "name": "1. FC Nürnberg",
            "id": "269",
            "slug": "1-fc-nurnberg"
        },
        "status": "Undisclosed"
    },
    {
        "date": "Jan 30",
        "player": {
            "id": "86454",
            "slug": "ivica-olic",
            "name": "Ivica Olic"
        },
        "fromClub": {
            "name": "VfL Wolfsburg",
            "id": "138",
            "slug": "vfl-wolfsburg"
        },
        "toClub": {
            "name": "Hamburg SV",
            "id": "127",
            "slug": "hamburg-sv"
        },
        "status": "Undisclosed"
    },
    {
        "date": "Jan 30",
        "player": {
            "id": "41786",
            "slug": "christoph-janker",
            "name": "Christoph Janker"
        },
        "fromClub": {
            "name": "Hertha Berlin",
            "id": "129",
            "slug": "hertha-berlin"
        },
        "toClub": {
            "name": "FC Augsburg",
            "id": "3841",
            "slug": "fc-augsburg"
        },
        "status": "Free"
    },
    {
        "date": "Jan 30",
        "player": {
            "id": null,
            "slug": null,
            "name": "Guilherme Biteco"
        },
        "fromClub": {
            "name": "TSG Hoffenheim",
            "id": "7911",
            "slug": "tsg-hoffenheim"
        },
        "toClub": {
            "name": "Santa Cruz",
            "id": "4929",
            "slug": "santa-cruz"
        },
        "status": "Loan"
    },
    {
        "date": "Jan 30",
        "player": {
            "id": "126620",
            "slug": "jiloan-hamad",
            "name": "Jiloan Hamad"
        },
        "fromClub": {
            "name": "TSG Hoffenheim",
            "id": "7911",
            "slug": "tsg-hoffenheim"
        },
        "toClub": {
            "name": "Standard Liege",
            "id": "559",
            "slug": "standard-liege"
        },
        "status": "Loan"
    },
    {
        "date": "Jan 30",
        "player": {
            "id": "147682",
            "slug": "olivier-occean",
            "name": "Olivier Occéan"
        },
        "fromClub": {
            "name": "Eintracht Frankfurt",
            "id": "125",
            "slug": "eintracht-frankfurt"
        },
        "toClub": {
            "name": "Odds BK",
            "id": "602",
            "slug": "odds-bk"
        },
        "status": "Loan"
    },
    {
        "date": "Jan 30",
        "player": {
            "id": "77705",
            "slug": "felipe-santana",
            "name": "Felipe Santana"
        },
        "fromClub": {
            "name": "Schalke 04",
            "id": "133",
            "slug": "schalke-04"
        },
        "toClub": {
            "name": "Olympiacos",
            "id": "435",
            "slug": "olympiacos"
        },
        "status": "Loan"
    },
    {
        "date": "Jan 30",
        "player": {
            "id": "196033",
            "slug": "valmir-sulejmani",
            "name": "Valmir Sulejmani"
        },
        "fromClub": {
            "name": "Hannover 96",
            "id": "2428",
            "slug": "hannover-96"
        },
        "toClub": {
            "name": "1. FC Union Berlin",
            "id": "598",
            "slug": "1-fc-union-berlin"
        },
        "status": "Loan"
    },
    {
        "date": "Jan 29",
        "player": {
            "id": "70463",
            "slug": "joao-pereira",
            "name": "João Pereira"
        },
        "fromClub": {
            "name": "Valencia",
            "id": "94",
            "slug": "valencia"
        },
        "toClub": {
            "name": "Hannover 96",
            "id": "2428",
            "slug": "hannover-96"
        },
        "status": "Free"
    },
    {
        "date": "Jan 29",
        "player": {
            "id": "153654",
            "slug": "simon-zoller",
            "name": "Simon Zoller"
        },
        "fromClub": {
            "name": "FC Cologne",
            "id": "122",
            "slug": "fc-cologne"
        },
        "toClub": {
            "name": "Kaiserslautern",
            "id": "130",
            "slug": "kaiserslautern"
        },
        "status": "Loan"
    },
    {
        "date": "Jan 28",
        "player": {
            "id": "135806",
            "slug": "tolgay-arslan",
            "name": "Tolgay Arslan"
        },
        "fromClub": {
            "name": "Hamburg SV",
            "id": "127",
            "slug": "hamburg-sv"
        },
        "toClub": {
            "name": "Besiktas",
            "id": "1895",
            "slug": "besiktas"
        },
        "status": "Undisclosed"
    },
    {
        "date": "Jan 28",
        "player": {
            "id": "154872",
            "slug": "raphael-holzhauser",
            "name": "Raphael Holzhauser"
        },
        "fromClub": {
            "name": "VfB Stuttgart",
            "id": "134",
            "slug": "vfb-stuttgart"
        },
        "toClub": {
            "name": "Austria Vienna",
            "id": "1382",
            "slug": "austria-vienna"
        },
        "status": "Undisclosed"
    },
    {
        "date": "Jan 28",
        "player": {
            "id": "196557",
            "slug": "jannik-bandowski",
            "name": "Jannik Bandowski"
        },
        "fromClub": {
            "name": "Borussia Dortmund",
            "id": "124",
            "slug": "borussia-dortmund"
        },
        "toClub": {
            "name": "TSV 1860 Munich",
            "id": "135",
            "slug": "tsv-1860-munich"
        },
        "status": "Loan"
    },
    {
        "date": "Jan 28",
        "player": {
            "id": "156359",
            "slug": "nicolas-castillo",
            "name": "Nicolás Castillo"
        },
        "fromClub": {
            "name": "Club Brugge",
            "id": "570",
            "slug": "club-brugge"
        },
        "toClub": {
            "name": "Mainz",
            "id": "2950",
            "slug": "mainz"
        },
        "status": "Loan"
    },
    {
        "date": "Jan 28",
        "player": {
            "id": "94936",
            "slug": "ludovic-obraniak",
            "name": "Ludovic Obraniak"
        },
        "fromClub": {
            "name": "Werder Bremen",
            "id": "137",
            "slug": "werder-bremen"
        },
        "toClub": {
            "name": "Caykur Rizespor",
            "id": "7656",
            "slug": "caykur-rizespor"
        },
        "status": "Loan"
    },
    {
        "date": "Jan 28",
        "player": {
            "id": "154546",
            "slug": "richard-strebinger",
            "name": "Richard Strebinger"
        },
        "fromClub": {
            "name": "Werder Bremen",
            "id": "137",
            "slug": "werder-bremen"
        },
        "toClub": {
            "name": "SSV Jahn Regensburg",
            "id": null,
            "slug": null
        },
        "status": "Loan"
    },
    {
        "date": "Jan 27",
        "player": {
            "id": "155211",
            "slug": "jannik-vestergaard",
            "name": "Jannik Vestergaard"
        },
        "fromClub": {
            "name": "TSG Hoffenheim",
            "id": "7911",
            "slug": "tsg-hoffenheim"
        },
        "toClub": {
            "name": "Werder Bremen",
            "id": "137",
            "slug": "werder-bremen"
        },
        "status": "Undisclosed"
    },
    {
        "date": "Jan 27",
        "player": {
            "id": "108385",
            "slug": "didier-ya-konan",
            "name": "Didier Ya Konan"
        },
        "fromClub": {
            "name": "Al-Ittihad",
            "id": null,
            "slug": null
        },
        "toClub": {
            "name": "Hannover 96",
            "id": "2428",
            "slug": "hannover-96"
        },
        "status": "Undisclosed"
    },
    {
        "date": "Jan 27",
        "player": {
            "id": "184550",
            "slug": "michael-zetterer",
            "name": "Michael Zetterer"
        },
        "fromClub": {
            "name": "SpVgg Unterhaching",
            "id": null,
            "slug": null
        },
        "toClub": {
            "name": "Werder Bremen",
            "id": "137",
            "slug": "werder-bremen"
        },
        "status": "Undisclosed"
    },
    {
        "date": "Jan 26",
        "player": {
            "id": "135806",
            "slug": "tolgay-arslan",
            "name": "Tolgay Arslan"
        },
        "fromClub": {
            "name": "Hamburg SV",
            "id": "127",
            "slug": "hamburg-sv"
        },
        "toClub": {
            "name": "Besiktas",
            "id": "1895",
            "slug": "besiktas"
        },
        "status": "Undisclosed"
    },
    {
        "date": "Jan 26",
        "player": {
            "id": null,
            "slug": null,
            "name": "Christian Rubio Sivodedov"
        },
        "fromClub": {
            "name": "Djurgården",
            "id": "2339",
            "slug": "djurgarden"
        },
        "toClub": {
            "name": "Schalke 04",
            "id": "133",
            "slug": "schalke-04"
        },
        "status": "Undisclosed"
    },
    {
        "date": "Jan 22",
        "player": {
            "id": "140079",
            "slug": "koen-casteels",
            "name": "Koen Casteels"
        },
        "fromClub": {
            "name": "VfL Wolfsburg",
            "id": "138",
            "slug": "vfl-wolfsburg"
        },
        "toClub": {
            "name": "Werder Bremen",
            "id": "137",
            "slug": "werder-bremen"
        },
        "status": "Loan"
    },
    {
        "date": "Jan 21",
        "player": {
            "id": "140079",
            "slug": "koen-casteels",
            "name": "Koen Casteels"
        },
        "fromClub": {
            "name": "TSG Hoffenheim",
            "id": "7911",
            "slug": "tsg-hoffenheim"
        },
        "toClub": {
            "name": "VfL Wolfsburg",
            "id": "138",
            "slug": "vfl-wolfsburg"
        },
        "status": "Undisclosed"
    },
    {
        "date": "Jan 20",
        "player": {
            "id": "183853",
            "slug": "tin-jedvaj",
            "name": "Tin Jedvaj"
        },
        "fromClub": {
            "name": "AS Roma",
            "id": "104",
            "slug": "as-roma"
        },
        "toClub": {
            "name": "Bayer Leverkusen",
            "id": "131",
            "slug": "bayer-leverkusen"
        },
        "status": "Undisclosed"
    },
    {
        "date": "Jan 16",
        "player": {
            "id": "174548",
            "slug": "hany-mukhtar",
            "name": "Hany Mukhtar"
        },
        "fromClub": {
            "name": "Hertha Berlin",
            "id": "129",
            "slug": "hertha-berlin"
        },
        "toClub": {
            "name": "Benfica",
            "id": "1929",
            "slug": "benfica"
        },
        "status": "Undisclosed"
    },
    {
        "date": "Jan 14",
        "player": {
            "id": "151765",
            "slug": "matija-nastasic",
            "name": "Matija Nastasic"
        },
        "fromClub": {
            "name": "Manchester City",
            "id": "382",
            "slug": "manchester-city"
        },
        "toClub": {
            "name": "Schalke 04",
            "id": "133",
            "slug": "schalke-04"
        },
        "status": "Loan"
    },
    {
        "date": "Jan 9",
        "player": {
            "id": "136775",
            "slug": "xherdan-shaqiri",
            "name": "Xherdan Shaqiri"
        },
        "fromClub": {
            "name": "Bayern Munich",
            "id": "132",
            "slug": "bayern-munich"
        },
        "toClub": {
            "name": "Internazionale",
            "id": "110",
            "slug": "internazionale"
        },
        "status": "Loan"
    },
    {
        "date": "Jan 7",
        "player": {
            "id": "144752",
            "slug": "philipp-wollscheid",
            "name": "Philipp Wollscheid"
        },
        "fromClub": {
            "name": "Bayer Leverkusen",
            "id": "131",
            "slug": "bayer-leverkusen"
        },
        "toClub": {
            "name": "Stoke City",
            "id": "336",
            "slug": "stoke-city"
        },
        "status": "Loan"
    },
    {
        "date": "Jan 6",
        "player": {
            "id": "136800",
            "slug": "christian-clemens",
            "name": "Christian Clemens"
        },
        "fromClub": {
            "name": "Schalke 04",
            "id": "133",
            "slug": "schalke-04"
        },
        "toClub": {
            "name": "Mainz",
            "id": "2950",
            "slug": "mainz"
        },
        "status": "Loan"
    },
    {
        "date": "Jan 3",
        "player": {
            "id": "46528",
            "slug": "eljero-elia",
            "name": "Eljero Elia"
        },
        "fromClub": {
            "name": "Werder Bremen",
            "id": "137",
            "slug": "werder-bremen"
        },
        "toClub": {
            "name": "Southampton",
            "id": "376",
            "slug": "southampton"
        },
        "status": "Loan"
    },
    {
        "date": "Jan 1",
        "player": {
            "id": "114898",
            "slug": "diego-benaglio",
            "name": "Diego Benaglio"
        },
        "fromClub": {
            "name": "Beijing Guoan",
            "id": null,
            "slug": null
        },
        "toClub": {
            "name": "VfL Wolfsburg",
            "id": "138",
            "slug": "vfl-wolfsburg"
        },
        "status": "Undisclosed"
    },
    {
        "date": "Jan 1",
        "player": {
            "id": "182347",
            "slug": "mats-daehli",
            "name": "Mats Daehli"
        },
        "fromClub": {
            "name": "Cardiff City",
            "id": "347",
            "slug": "cardiff-city"
        },
        "toClub": {
            "name": "SC Freiburg",
            "id": "126",
            "slug": "sc-freiburg"
        },
        "status": "Undisclosed"
    },
    {
        "date": "Jan 1",
        "player": {
            "id": "150375",
            "slug": "ji-dong-won",
            "name": "Ji Dong-Won"
        },
        "fromClub": {
            "name": "Borussia Dortmund",
            "id": "124",
            "slug": "borussia-dortmund"
        },
        "toClub": {
            "name": "FC Augsburg",
            "id": "3841",
            "slug": "fc-augsburg"
        },
        "status": "Undisclosed"
    },
    {
        "date": "Jan 1",
        "player": {
            "id": "141055",
            "slug": "kevin-kampl",
            "name": "Kevin Kampl"
        },
        "fromClub": {
            "name": "RB Salzburg",
            "id": "2790",
            "slug": "rb-salzburg"
        },
        "toClub": {
            "name": "Borussia Dortmund",
            "id": "124",
            "slug": "borussia-dortmund"
        },
        "status": "Undisclosed"
    },
    {
        "date": "Jan 1",
        "player": {
            "id": "138157",
            "slug": "knowledge-musona",
            "name": "Knowledge Musona"
        },
        "fromClub": {
            "name": "TSG Hoffenheim",
            "id": "7911",
            "slug": "tsg-hoffenheim"
        },
        "toClub": {
            "name": "KV Oostende",
            "id": "3612",
            "slug": "kv-oostende"
        },
        "status": "Undisclosed"
    },
    {
        "date": "Jan 1",
        "player": {
            "id": "188054",
            "slug": "florian-ballas",
            "name": "Florian Ballas"
        },
        "fromClub": {
            "name": "Hannover 96",
            "id": "2428",
            "slug": "hannover-96"
        },
        "toClub": {
            "name": "Eintracht Frankfurt",
            "id": "125",
            "slug": "eintracht-frankfurt"
        },
        "status": "Free"
    },
    {
        "date": "Jan 1",
        "player": {
            "id": "139644",
            "slug": "julian-koch",
            "name": "Julian Koch"
        },
        "fromClub": {
            "name": "Mainz",
            "id": "2950",
            "slug": "mainz"
        },
        "toClub": {
            "name": "St. Pauli",
            "id": "270",
            "slug": "st-pauli"
        },
        "status": "Loan"
    },
    {
        "date": "Jan 1",
        "player": {
            "id": "109312",
            "slug": "nils-petersen",
            "name": "Nils Petersen"
        },
        "fromClub": {
            "name": "Werder Bremen",
            "id": "137",
            "slug": "werder-bremen"
        },
        "toClub": {
            "name": "SC Freiburg",
            "id": "126",
            "slug": "sc-freiburg"
        },
        "status": "Loan"
    },
    {
        "date": "Jan 1",
        "player": {
            "id": "186171",
            "slug": "vladimir-rankovic",
            "name": "Vladimir Rankovic"
        },
        "fromClub": {
            "name": "Hannover 96",
            "id": "2428",
            "slug": "hannover-96"
        },
        "toClub": {
            "name": "FC Erzgebirge Aue",
            "id": "3849",
            "slug": "fc-erzgebirge-aue"
        },
        "status": "Loan"
    },
    {
        "date": "Jan 1",
        "player": {
            "id": "188058",
            "slug": "levin-oztunali",
            "name": "Levin Öztunali"
        },
        "fromClub": {
            "name": "Bayer Leverkusen",
            "id": "131",
            "slug": "bayer-leverkusen"
        },
        "toClub": {
            "name": "Werder Bremen",
            "id": "137",
            "slug": "werder-bremen"
        },
        "status": "Loan"
    }
]